GainloMianshiZhinan/README.md
GainloMianshiZhinan/__init__.py
GainloMianshiZhinan/__main__.py
GainloMianshiZhinan/file.epub
GainloMianshiZhinan/index.html
GainloMianshiZhinan/css/__init__.py
GainloMianshiZhinan/css/annotations.css
GainloMianshiZhinan/css/main.css
GainloMianshiZhinan/css/normalize.css
GainloMianshiZhinan/css/popup.css
GainloMianshiZhinan/font/__init__.py
GainloMianshiZhinan/font/fontello.eot
GainloMianshiZhinan/font/fontello.svg
GainloMianshiZhinan/font/fontello.ttf
GainloMianshiZhinan/font/fontello.woff
GainloMianshiZhinan/img/__init__.py
GainloMianshiZhinan/img/annotator-glyph-sprite.png
GainloMianshiZhinan/img/annotator-icon-sprite.png
GainloMianshiZhinan/img/apple-touch-icon.png
GainloMianshiZhinan/img/cancelfullscreen.png
GainloMianshiZhinan/img/close.png
GainloMianshiZhinan/img/fullscreen.png
GainloMianshiZhinan/img/loader.gif
GainloMianshiZhinan/img/menu-icon.png
GainloMianshiZhinan/img/save.png
GainloMianshiZhinan/img/saved.png
GainloMianshiZhinan/img/settings-s.png
GainloMianshiZhinan/img/settings.png
GainloMianshiZhinan/img/star.png
GainloMianshiZhinan/js/__init__.py
GainloMianshiZhinan/js/epub.js
GainloMianshiZhinan/js/epub.min.js
GainloMianshiZhinan/js/epub.min.map
GainloMianshiZhinan/js/hooks.min.js
GainloMianshiZhinan/js/hooks.min.map
GainloMianshiZhinan/js/reader.js
GainloMianshiZhinan/js/reader.js.map
GainloMianshiZhinan/js/reader.min.js
GainloMianshiZhinan/js/reader.min.map
GainloMianshiZhinan/js/hooks/__init__.py
GainloMianshiZhinan/js/hooks/extensions/__init__.py
GainloMianshiZhinan/js/hooks/extensions/highlight.js
GainloMianshiZhinan/js/libs/__init__.py
GainloMianshiZhinan/js/libs/jquery.min.js
GainloMianshiZhinan/js/libs/localforage.min.js
GainloMianshiZhinan/js/libs/screenfull.js
GainloMianshiZhinan/js/libs/screenfull.min.js
GainloMianshiZhinan/js/libs/zip.min.js
GainloMianshiZhinan/js/plugins/__init__.py
GainloMianshiZhinan/js/plugins/hypothesis.js
GainloMianshiZhinan/js/plugins/search.js
gainlo_mianshi_zhinan-2024.3.2.0.dist-info/METADATA
gainlo_mianshi_zhinan-2024.3.2.0.dist-info/WHEEL
gainlo_mianshi_zhinan-2024.3.2.0.dist-info/entry_points.txt
gainlo_mianshi_zhinan-2024.3.2.0.dist-info/top_level.txt
gainlo_mianshi_zhinan-2024.3.2.0.dist-info/RECORD
